{
  "dataType": "TextOnly",
  "data": [
    [
      {
        "title": "임차권등기명령이란? 🏠",
        "contentSections": [
          {
            "subtitle": "보증금 보호를 위한 법적 절차",
            "contents": [
              "임차권등기명령은 전세금 반환을 받지 못한 상황에서 이사를 해야 할 때 사용하는 법적 절차입니다. 이 절차를 완료하면 새로운 집으로 이사하더라도 기존 보증금에 대한 대항력을 유지할 수 있습니다. 등기부등본에 '주택임차권'이 표시되어 임대인이 마음대로 다음 세입자를 입주시킬 수 없게 됩니다."
            ]
          },
          {
            "subtitle": "대항력과 우선변제권의 의미",
            "contents": [
              "• 대항력: 임대인이 다른 사람에게 집을 임대하더라도 내 권리를 주장할 수 있는 힘",
              "• 우선변제권: 집이 경매될 때 내 보증금을 우선적으로 받을 수 있는 권리",
              "• 임차권등기: 등기부에 내 임차권이 공식적으로 기록되는 것"
            ]
          }
        ],
        "image": {
          "src": "https://ibbiu.com/wp-content/uploads/2024/01/%EC%9E%84%EC%B0%A8%EA%B6%8C%EB%93%B1%EA%B8%B0%EB%AA%85%EB%A0%B9-%EB%93%B1%EA%B8%B0%EB%B6%80%EB%93%B1%EB%B3%B8.png",
          "alt": "등기부등본 주택임차권 표시 샘플 이미지",
          "width": 400,
          "height": 300
        }
      }
    ],
    [
      {
        "title": "언제 임차권등기명령을 신청해야 할까요? ⏰",
        "contentSections": [
          {
            "subtitle": "긴급한 이사가 필요한 상황",
            "contents": [
              "• 임대인이 전세금을 반환하지 않아 법적 분쟁이 발생한 경우",
              "• 계약 기간이 만료되었지만 보증금을 돌려받지 못한 경우",
              "• 새로운 집을 구해야 하는데 기존 보증금이 필요한 경우",
              "• 임대인이 집을 팔거나 다른 사람에게 임대하려는 경우"
            ]
          },
          {
            "subtitle": "신청 시점의 중요성",
            "contents": [
              "• 이사하기 전에 반드시 신청해야 합니다",
              "• 이미 이사한 후에는 신청이 어려울 수 있습니다",
              "• 임대인과의 분쟁이 시작되기 전에 미리 준비하는 것이 좋습니다"
            ]
          }
        ]
      }
    ],
    [
      {
        "title": "임차권등기명령 신청 절차 📋",
        "contentSections": [
          {
            "subtitle": "1단계: 신청서 작성 및 준비",
            "contents": [
              "• 임차권등기명령 신청서 작성 (법원 양식 사용)",
              "• 임대차계약서 사본 준비",
              "• 전세금 지급 증빙서류 준비 (입금증, 통장 등)",
              "• 임대인 주소 확인서류 준비"
            ]
          },
          {
            "subtitle": "2단계: 법원에 신청서 제출",
            "contents": [
              "• 관할 법원에 신청서 제출 (임대인 주소지 관할 법원)",
              "• 신청 수수료 납부 (약 1-2만원)",
              "• 증빙서류 함께 제출"
            ]
          },
          {
            "subtitle": "3단계: 법원 심사 및 결정",
            "contents": [
              "• 법원에서 신청서와 증빙서류 심사",
              "• 임차권이 인정되면 임차권등기명령 결정",
              "• 결정문을 임대인에게 송달"
            ]
          }
        ]
      }
    ],
    [
      {
        "title": "등기부등본 확인의 중요성 🔍",
        "contentSections": [
          {
            "subtitle": "내가 살 집의 등기부등본 확인",
            "contents": [
              "• 새로운 집을 구할 때 반드시 등기부등본을 확인하세요",
              "• '주택임차권' 표시가 있다면 이전 세입자가 아직 보증금을 돌려받지 못했다는 뜻입니다",
              "• 이런 집은 임대인과의 분쟁이 있을 수 있어 계약에 신중해야 합니다"
            ]
          },
          {
            "subtitle": "등기부등본에서 확인할 점",
            "contents": [
              "• 주택임차권 등기 여부",
              "• 임차권자(세입자)의 이름",
              "• 임차권 설정일자",
              "• 임차권 말소 여부"
            ]
          }
        ],
        "summary": "💡 등기부등본은 집을 구할 때 반드시 확인해야 하는 중요한 서류입니다. 임차권 표시 여부로 집의 안전성을 판단할 수 있어요."
      }
    ],
    [
      {
        "title": "임차권등기명령의 효과와 한계 ⚖️",
        "contentSections": [
          {
            "subtitle": "긍정적 효과",
            "contents": [
              "• 보증금에 대한 대항력 유지",
              "• 임대인의 무단 임대 방지",
              "• 경매 시 우선변제권 확보",
              "• 법적 권리 보호"
            ]
          },
          {
            "subtitle": "주의사항과 한계",
            "contents": [
              "• 임대인이 이의를 제기할 수 있음",
              "• 실제 집행은 별도 절차 필요",
              "• 임대인에게 재산이 없으면 집행 어려움",
              "• 복잡한 법적 분쟁 시 추가 소송 필요"
            ]
          }
        ]
      }
    ],
    [
      {
        "title": "등기부등본 발급 및 확인 🚀",
        "contentSections": [
          {
            "subtitle": "온라인 발급",
            "contents": [
              "• 대법원 인터넷등기소에서 24시간 발급 가능",
              "• 본인인증 후 즉시 발급",
              "• 수수료: 600원 (온라인 발급 시)"
            ]
          },
          {
            "subtitle": "방문 발급",
            "contents": [
              "• 관할 등기소에 직접 방문하여 발급",
              "• 신분증 지참 필요",
              "• 수수료: 1,200원 (방문 발급 시)"
            ]
          }
        ],
        "buttons": [
          {
            "text": "대법원 인터넷등기소 바로가기",
            "variant": "primary",
            "href": "https://ecf.scourt.go.kr/",
            "fullWidth": true
          },
          {
            "text": "등기부등본 발급 가이드 보기",
            "variant": "secondary",
            "href": "https://www.scourt.go.kr/portal/information/guide/guide_01.jsp",
            "fullWidth": true
          }
        ]
      }
    ]
  ]
}
